{"current_program_scene":"desktop","current_scene":"desktop","current_transition":"Fade","groups":[{"balance":0.5,"deinterlace_field_order":0,"deinterlace_mode":0,"enabled":true,"flags":0,"hotkeys":{"libobs.hide_scene_item.01-02-dtop":[],"libobs.hide_scene_item.01-03-cllr":[],"libobs.hide_scene_item.01-04-mic01":[],"libobs.hide_scene_item.01-05-mic02":[],"libobs.show_scene_item.01-02-dtop":[],"libobs.show_scene_item.01-03-cllr":[],"libobs.show_scene_item.01-04-mic01":[],"libobs.show_scene_item.01-05-mic02":[]},"id":"group","mixers":0,"monitoring_type":0,"muted":false,"name":"snd","prev_ver":486539266,"private_settings":{},"push-to-mute":false,"push-to-mute-delay":0,"push-to-talk":false,"push-to-talk-delay":0,"settings":{"custom_size":true,"cx":0,"cy":0,"id_counter":0,"items":[{"align":5,"blend_method":"default","blend_type":"normal","bounds":{"x":0.0,"y":0.0},"bounds_align":0,"bounds_type":0,"crop_bottom":0,"crop_left":0,"crop_right":0,"crop_top":0,"group_item_backup":false,"hide_transition":{"duration":0},"id":9,"locked":true,"name":"01-05-mic02","pos":{"x":0.0,"y":0.0},"private_settings":{},"rot":0.0,"scale":{"x":1.0,"y":1.0},"scale_filter":"disable","show_transition":{"duration":0},"visible":true},{"align":5,"blend_method":"default","blend_type":"normal","bounds":{"x":0.0,"y":0.0},"bounds_align":0,"bounds_type":0,"crop_bottom":0,"crop_left":0,"crop_right":0,"crop_top":0,"group_item_backup":false,"hide_transition":{"duration":0},"id":5,"locked":true,"name":"01-04-mic01","pos":{"x":0.0,"y":0.0},"private_settings":{},"rot":0.0,"scale":{"x":1.0,"y":1.0},"scale_filter":"disable","show_transition":{"duration":0},"visible":true},{"align":5,"blend_method":"default","blend_type":"normal","bounds":{"x":0.0,"y":0.0},"bounds_align":0,"bounds_type":0,"crop_bottom":0,"crop_left":0,"crop_right":0,"crop_top":0,"group_item_backup":false,"hide_transition":{"duration":0},"id":4,"locked":true,"name":"01-03-cllr","pos":{"x":0.0,"y":0.0},"private_settings":{},"rot":0.0,"scale":{"x":1.0,"y":1.0},"scale_filter":"disable","show_transition":{"duration":0},"visible":true},{"align":5,"blend_method":"default","blend_type":"normal","bounds":{"x":0.0,"y":0.0},"bounds_align":0,"bounds_type":0,"crop_bottom":0,"crop_left":0,"crop_right":0,"crop_top":0,"group_item_backup":false,"hide_transition":{"duration":0},"id":3,"locked":true,"name":"01-02-dtop","pos":{"x":0.0,"y":0.0},"private_settings":{},"rot":0.0,"scale":{"x":1.0,"y":1.0},"scale_filter":"disable","show_transition":{"duration":0},"visible":true}]},"sync":0,"versioned_id":"group","volume":1.0}],"modules":{"auto-scene-switcher":{"active":false,"interval":300,"non_matching_scene":"","switch_if_not_matching":false,"switches":[]},"output-timer":{"autoStartRecordTimer":false,"autoStartStreamTimer":false,"pauseRecordTimer":true,"recordTimerHours":0,"recordTimerMinutes":0,"recordTimerSeconds":30,"streamTimerHours":0,"streamTimerMinutes":0,"streamTimerSeconds":30},"scripts-tool":[]},"name":"screen-multi","preview_locked":false,"quick_transitions":[{"duration":300,"fade_to_black":false,"hotkeys":[],"id":1,"name":"Cut"},{"duration":300,"fade_to_black":false,"hotkeys":[],"id":2,"name":"Fade"},{"duration":300,"fade_to_black":true,"hotkeys":[],"id":3,"name":"Fade"}],"saved_projectors":[],"scaling_enabled":false,"scaling_level":0,"scaling_off_x":0.0,"scaling_off_y":0.0,"scene_order":[{"name":"desktop"}],"sources":[{"balance":0.5,"deinterlace_field_order":0,"deinterlace_mode":0,"enabled":true,"flags":0,"hotkeys":{"libobs.mute":[],"libobs.push-to-mute":[],"libobs.push-to-talk":[],"libobs.unmute":[]},"id":"pulse_input_capture","mixers":201,"monitoring_type":0,"muted":false,"name":"01-04-mic01","prev_ver":486539266,"private_settings":{"volume_locked":true},"push-to-mute":false,"push-to-mute-delay":0,"push-to-talk":false,"push-to-talk-delay":0,"settings":{"device_id":"mic01-processed"},"sync":0,"versioned_id":"pulse_input_capture","volume":1.0},{"balance":0.5,"deinterlace_field_order":0,"deinterlace_mode":0,"enabled":true,"flags":0,"hotkeys":{"libobs.mute":[],"libobs.push-to-mute":[],"libobs.push-to-talk":[],"libobs.unmute":[]},"id":"pulse_output_capture","mixers":197,"monitoring_type":0,"muted":false,"name":"01-03-cllr","prev_ver":486539266,"private_settings":{"volume_locked":true},"push-to-mute":false,"push-to-mute-delay":0,"push-to-talk":false,"push-to-talk-delay":0,"settings":{"device_id":"from-caller.monitor"},"sync":0,"versioned_id":"pulse_output_capture","volume":1.0},{"balance":0.5,"deinterlace_field_order":0,"deinterlace_mode":0,"enabled":true,"flags":0,"hotkeys":{"libobs.mute":[],"libobs.push-to-mute":[],"libobs.push-to-talk":[],"libobs.unmute":[]},"id":"pulse_output_capture","mixers":195,"monitoring_type":0,"muted":false,"name":"01-02-dtop","prev_ver":486539266,"private_settings":{"volume_locked":true},"push-to-mute":false,"push-to-mute-delay":0,"push-to-talk":false,"push-to-talk-delay":0,"settings":{"device_id":"from-desktop.monitor"},"sync":0,"versioned_id":"pulse_output_capture","volume":1.0},{"balance":0.5,"deinterlace_field_order":0,"deinterlace_mode":0,"enabled":true,"flags":0,"hotkeys":{},"id":"xshm_input","mixers":0,"monitoring_type":0,"muted":false,"name":"screen","prev_ver":486539266,"private_settings":{},"push-to-mute":false,"push-to-mute-delay":0,"push-to-talk":false,"push-to-talk-delay":0,"settings":{"screen":1},"sync":0,"versioned_id":"xshm_input","volume":1.0},{"balance":0.5,"deinterlace_field_order":0,"deinterlace_mode":0,"enabled":true,"flags":0,"hotkeys":{"OBSBasic.SelectScene":[],"libobs.hide_scene_item.screen":[],"libobs.hide_scene_item.snd":[],"libobs.show_scene_item.screen":[],"libobs.show_scene_item.snd":[]},"id":"scene","mixers":0,"monitoring_type":0,"muted":false,"name":"desktop","prev_ver":486539266,"private_settings":{},"push-to-mute":false,"push-to-mute-delay":0,"push-to-talk":false,"push-to-talk-delay":0,"settings":{"custom_size":false,"id_counter":9,"items":[{"align":5,"blend_method":"default","blend_type":"normal","bounds":{"x":1920.0,"y":1080.0},"bounds_align":0,"bounds_type":2,"crop_bottom":0,"crop_left":0,"crop_right":0,"crop_top":0,"group_item_backup":false,"hide_transition":{"duration":0},"id":2,"locked":true,"name":"screen","pos":{"x":0.0,"y":0.0},"private_settings":{},"rot":0.0,"scale":{"x":1.0,"y":1.0},"scale_filter":"disable","show_transition":{"duration":0},"visible":true},{"align":5,"blend_method":"default","blend_type":"normal","bounds":{"x":0.0,"y":0.0},"bounds_align":0,"bounds_type":0,"crop_bottom":0,"crop_left":0,"crop_right":0,"crop_top":0,"group_item_backup":true,"hide_transition":{"duration":0},"id":9,"locked":true,"name":"01-05-mic02","pos":{"x":0.0,"y":0.0},"private_settings":{},"rot":0.0,"scale":{"x":1.0,"y":1.0},"scale_filter":"disable","show_transition":{"duration":0},"visible":true},{"align":5,"blend_method":"default","blend_type":"normal","bounds":{"x":0.0,"y":0.0},"bounds_align":0,"bounds_type":0,"crop_bottom":0,"crop_left":0,"crop_right":0,"crop_top":0,"group_item_backup":true,"hide_transition":{"duration":0},"id":5,"locked":true,"name":"01-04-mic01","pos":{"x":0.0,"y":0.0},"private_settings":{},"rot":0.0,"scale":{"x":1.0,"y":1.0},"scale_filter":"disable","show_transition":{"duration":0},"visible":true},{"align":5,"blend_method":"default","blend_type":"normal","bounds":{"x":0.0,"y":0.0},"bounds_align":0,"bounds_type":0,"crop_bottom":0,"crop_left":0,"crop_right":0,"crop_top":0,"group_item_backup":true,"hide_transition":{"duration":0},"id":4,"locked":true,"name":"01-03-cllr","pos":{"x":0.0,"y":0.0},"private_settings":{},"rot":0.0,"scale":{"x":1.0,"y":1.0},"scale_filter":"disable","show_transition":{"duration":0},"visible":true},{"align":5,"blend_method":"default","blend_type":"normal","bounds":{"x":0.0,"y":0.0},"bounds_align":0,"bounds_type":0,"crop_bottom":0,"crop_left":0,"crop_right":0,"crop_top":0,"group_item_backup":true,"hide_transition":{"duration":0},"id":3,"locked":true,"name":"01-02-dtop","pos":{"x":0.0,"y":0.0},"private_settings":{},"rot":0.0,"scale":{"x":1.0,"y":1.0},"scale_filter":"disable","show_transition":{"duration":0},"visible":true},{"align":5,"blend_method":"default","blend_type":"normal","bounds":{"x":0.0,"y":0.0},"bounds_align":0,"bounds_type":0,"crop_bottom":0,"crop_left":0,"crop_right":0,"crop_top":0,"group_item_backup":false,"hide_transition":{"duration":0},"id":1,"locked":true,"name":"snd","pos":{"x":0.0,"y":0.0},"private_settings":{"collapsed":false},"rot":0.0,"scale":{"x":1.0,"y":1.0},"scale_filter":"disable","show_transition":{"duration":0},"visible":true}]},"sync":0,"versioned_id":"scene","volume":1.0},{"balance":0.5,"deinterlace_field_order":0,"deinterlace_mode":0,"enabled":true,"flags":0,"hotkeys":{"libobs.mute":[],"libobs.push-to-mute":[],"libobs.push-to-talk":[],"libobs.unmute":[]},"id":"pulse_input_capture","mixers":209,"monitoring_type":0,"muted":false,"name":"01-05-mic02","prev_ver":486539266,"private_settings":{"volume_locked":true},"push-to-mute":false,"push-to-mute-delay":0,"push-to-talk":false,"push-to-talk-delay":0,"settings":{"device_id":"mic02-processed"},"sync":0,"versioned_id":"pulse_input_capture","volume":1.0}],"transition_duration":300,"transitions":[],"virtual-camera":{"internal":0,"scene":"","source":"","type":0}}